{
	"schemaVersion": 1,
	"id": "difficultymod",
	"version": "${version}",
	"name": "The Masochist Difficulty",
	"description": "A Masochist difficulty for Minecraft, you have been warned.",
	"authors": [
		"Jasper Clarke <me@jasperclarke.com>"
	],
	"contact": {
		"homepage": "https://jasperclarke.com",
		"sources": "https://github.com/FabricMC/fabric-example-mod"
	},
	"license": "MIT",
	"icon": "assets/difficultymod/icon.png",
	"environment": "*",
	"entrypoints": {
		"main": [
			"com.jasperclarke.difficultymod.DifficultyMod"
		],
		"fabric-datagen": [
			"com.jasperclarke.difficultymod.DifficultyModDataGenerator"
		],
		"client": [
			"com.jasperclarke.difficultymod.DifficultyModClient"
		]
	},
	"mixins": [
		"difficultymod.mixins.json"
	],
	"depends": {
		"fabricloader": ">=0.16.9",
		"minecraft": "~1.21.3",
		"java": ">=21",
		"fabric-api": "*"
	},
	"suggests": {
		"another-mod": "*"
	}
}